fulgur/__init__.py
fulgur/call_py.py
fulgur/classification.py
fulgur/model.py
fulgur/regression.py
fulgur/utils.py
fulgur-0.1.2.dist-info/METADATA
fulgur-0.1.2.dist-info/WHEEL
fulgur-0.1.2.dist-info/licenses/LICENSE
fulgur-0.1.2.dist-info/RECORD
