Metadata-Version: 2.4
Name: fulgur
Version: 0.1.2
Summary: Estimate linear models on extremely large (potentially out-of-core) datasets.
Author-email: Daniel Molitor <molitdj97@gmail.com>
License-File: LICENSE
Requires-Python: >=3.11
Requires-Dist: cloudpickle>=3.1.2
Requires-Dist: formulaic>=1.2.1
Requires-Dist: polars>=1.35.2
Requires-Dist: pyarrow>=22.0.0
Requires-Dist: scikit-learn==1.7.2
Requires-Dist: tqdm>=4.67.1
